cpfgen/__init__.py
cpfgen/cpfgen.py
cpfgen-1.0.4.dist-info/LICENSE
cpfgen-1.0.4.dist-info/METADATA
cpfgen-1.0.4.dist-info/WHEEL
cpfgen-1.0.4.dist-info/top_level.txt
cpfgen-1.0.4.dist-info/RECORD
