Metadata-Version: 2.1
Name: cpfgen
Version: 1.0.4
Summary: A simple CLI application that prints a valid CPF number.
Home-page: https://github.com/rodrigorichter/cpfgen
Author: Rodrigo Richter
Author-email: guigorichter@gmail.com
License: UNKNOWN
Platform: UNKNOWN
Classifier: Programming Language :: Python :: 3
Classifier: License :: OSI Approved :: MIT License
Classifier: Operating System :: OS Independent
Requires-Python: >=3.6
